LICENSE
MANIFEST.in
README
setup.py
src/sleipnir/__init__.py
src/sleipnir.bank.egg-info/PKG-INFO
src/sleipnir.bank.egg-info/SOURCES.txt
src/sleipnir.bank.egg-info/dependency_links.txt
src/sleipnir.bank.egg-info/namespace_packages.txt
src/sleipnir.bank.egg-info/not-zip-safe
src/sleipnir.bank.egg-info/requires.txt
src/sleipnir.bank.egg-info/top_level.txt
src/sleipnir/bank/__init__.py
src/sleipnir/bank/bank.py
src/sleipnir/bank/client.py
src/sleipnir/bank/constants.py
src/sleipnir/bank/gateways.py
src/sleipnir/bank/loanbroker.py
src/sleipnir/bank/messages.py
src/sleipnir/bank/routes.py
src/sleipnir/bank/scoring.py
src/sleipnir/bank/setup.py